chainpoint3.py
tests/__init__.py
tests/chainpoint_test.py
chainpoint3-0.1.1.dist-info/LICENSE
chainpoint3-0.1.1.dist-info/METADATA
chainpoint3-0.1.1.dist-info/WHEEL
chainpoint3-0.1.1.dist-info/top_level.txt
chainpoint3-0.1.1.dist-info/RECORD
