Metadata-Version: 2.1
Name: chainpoint3
Version: 0.1.1
Summary: Chainpoint proof of existence library
Home-page: https://github.com/GitTiago/pychainpoint
Author: Tiago Santos
License: MIT
Keywords: proof of existence,blockchain,merkle tree
Platform: UNKNOWN
Classifier: Intended Audience :: Developers
Classifier: Intended Audience :: Science/Research
Classifier: License :: OSI Approved :: MIT License
Classifier: Programming Language :: Python :: 3
Requires-Dist: merkletools
